yta_video_pyav/__init__.py
yta_video_pyav/reader/__init__.py
yta_video_pyav/reader/cache/__init__.py
yta_video_pyav/reader/cache/audio.py
yta_video_pyav/reader/cache/utils.py
yta_video_pyav/reader/cache/video.py
yta_video_pyav/reader/filter/__init__.py
yta_video_pyav/reader/filter/dataclass.py
yta_video_pyav/reader/filter/utils.py
yta_video_pyav/settings.py
yta_video_pyav/utils.py
yta_video_pyav/writer.py
yta_video_pyav-0.3.14.dist-info/licenses/LICENSE
yta_video_pyav-0.3.14.dist-info/METADATA
yta_video_pyav-0.3.14.dist-info/WHEEL
yta_video_pyav-0.3.14.dist-info/RECORD
