Metadata-Version: 2.4
Name: yta-video-pyav
Version: 0.3.14
Summary: Youtube Autonomous Video PyAv Module
License-File: LICENSE
Author: danialcala94
Author-email: danielalcalavalera@gmail.com
Requires-Python: ==3.9
Classifier: Programming Language :: Python :: 3
Classifier: Programming Language :: Python :: 3.9
Requires-Dist: av (>=0.0.1,<99.0.0)
Requires-Dist: numpy (>=0.0.1,<9.0.0)
Requires-Dist: quicktions (>=0.0.1,<9.0.0)
Requires-Dist: yta_constants (>=0.0.1,<1.0.0)
Requires-Dist: yta_validation (>=0.0.1,<1.0.0)
Requires-Dist: yta_video_frame_time (>=0.0.1,<1.0.0)
